{"name":"basket basket-consumer-api-v2-gu-jp ALB HTTPCode_Target_4XX_Count Warn","arn":"arn:aws:cloudwatch:ap-northeast-1:174683876178:alarm:basket basket-consumer-api-v2-gu-jp ALB HTTPCode_Target_4XX_Count Warn","state":"ALARM","dimensions":[{"Name":"TargetGroup","Value":"targetgroup/basket-consumer-api-v2-gu-jp/9b7d382426be82fb"},{"Name":"LoadBalancer","Value":"app/basket-cs-intr-alb/0876cb84093a8553"}],"metric":"HTTPCode_Target_4XX_Count","reason":"Threshold Crossed: 1 datapoint [43.0 (18/01/22 19:42:00)] was greater than or equal to the threshold (30.0).","namespace":"AWS/ApplicationELB"}
{"name":"basket basket-consumer-api-v2-uq-jp ALB HTTPCode_Target_4XX_Count Warn","arn":"arn:aws:cloudwatch:ap-northeast-1:174683876178:alarm:basket basket-consumer-api-v2-uq-jp ALB HTTPCode_Target_4XX_Count Warn","state":"ALARM","dimensions":[{"Name":"TargetGroup","Value":"targetgroup/basket-consumer-api-v2-uq-jp/cb06c84a4baa70c5"},{"Name":"LoadBalancer","Value":"app/basket-cs-intr-alb/0876cb84093a8553"}],"metric":"HTTPCode_Target_4XX_Count","reason":"Threshold Crossed: 1 datapoint [32.0 (06/03/22 19:06:00)] was greater than or equal to the threshold (30.0).","namespace":"AWS/ApplicationELB"}
{"name":"basket basket-consumer-kong-oss ALB HTTPCode_Target_4XX_Count Warn","arn":"arn:aws:cloudwatch:ap-northeast-1:174683876178:alarm:basket basket-consumer-kong-oss ALB HTTPCode_Target_4XX_Count Warn","state":"ALARM","dimensions":[{"Name":"LoadBalancer","Value":"app/basket-consumer-alb/c2ce77ef2e99c011"},{"Name":"TargetGroup","Value":"targetgroup/basket-consumer-kong-oss/c6406ed832a63196"}],"metric":"HTTPCode_Target_4XX_Count","reason":"Threshold Crossed: 1 datapoint [91.0 (22/02/22 05:23:00)] was greater than or equal to the threshold (30.0).","namespace":"AWS/ApplicationELB"}
